json_to_df/__init__.py
json_to_df/json_to_df.py
json_to_df-0.0.1.dist-info/LICENSE
json_to_df-0.0.1.dist-info/METADATA
json_to_df-0.0.1.dist-info/WHEEL
json_to_df-0.0.1.dist-info/top_level.txt
json_to_df-0.0.1.dist-info/RECORD
