Metadata-Version: 2.1
Name: json_to_df
Version: 0.0.1
Summary: Package to convert nested JSON to dataframes
Home-page: https://github.com/SourinKarmakar/json_to_df
Author: Sourin Karmakar
Author-email: sourinkarmakar@gmail.com
License-File: LICENSE
